Workbook

Sheet Introduction
A1: Lab-2 : ANP-D6305 -> Explain all the functions in Excel (Theory + Formula)
A2: Name: Asutosh Sunil Desai
A4: What is MS Excel?
A5: Microsoft Excel is a spreadsheet application used to store, organise, calculate and analyse data in rows and columns.
A6: A workbook contains sheets; a sheet is a grid of cells. Each cell has an address such as A1 (column A, row 1).
A8: Formula vs Function
A9: Formula: an expression written by the user that starts with '=' , e.g. =A1+B1*2
A10: Function: a built-in, predefined formula with a name and arguments, e.g. =SUM(A1:A10)
A11: Syntax of a function: =FUNCTION_NAME(argument1, argument2, ...)
A13: Types of Cell References
A14: Relative (A1) : changes when the formula is copied to another cell.
A15: Absolute ($A$1): stays fixed when copied (press F4 to add $).
... A28: Change any value in the 'Data' sheet and the results in the 'Functions' sheet update automatically.

Sheet Data
A1: Emp ID | B1: Name | C1: Department | D1: City | E1: Salary (Rs) | F1: Join Date | G1: Sales Q1 (Rs) | H1: Rating
A2: 101 | B2: rahul sharma | C2: Sales | D2: Mumbai | E2: 45000 | F2: 44270 | G2: 120000 | H2: 4
A3: 102 | B3: Priya Patil | C3: HR | D3: Pune | E3: 38000 | F3: 44013 | G3: 0 | H3: 5
A4: 103 | B4: Amit Joshi | C4: IT | D4: Mumbai | E4: 62000 | F4: 43475 | G4: 0 | H4: 3
A5: 104 | B5: Sneha Kulkarni | C5: Sales | D5: Thane | E5: 41000 | F5: 44885 | G5: 98000 | H5: 4
A6: 105 | B6: Rohan Mehta | C6: IT | D6: Pune | E6: 58000 | F6: 43225 | G6: 0 | H6: 5
A7: 106 | B7: Neha Desai | C7: Finance | D7: Mumbai | E7: 52000 | F7: 44451 | G7: 0 | H7: 4
A8: 107 | B8: Karan Shah | C8: Sales | D8: Virar | E8: 39000 | F8: 44958 | G8: 150000 | H8: 3
A9: 108 | B9: Pooja Naik | C9: Finance | D9: Thane | E9: 47000 | F9: 44183 | G9: 0 | H9: 2
A10: 109 | B10: Vikas More | C10: IT | D10: Virar | E10: 65000 | F10: 42972 | G10: 0 | H10: 4
A11: 110 | B11: Anjali Rao | C11: Sales | D11: Pune | E11: 43000 | F11: 44742 | G11: 87000 | H11: 5
A13: Horizontal table (used by HLOOKUP)
A14: Month | B14: Jan | C14: Feb | D14: Mar | E14: Apr | F14: May | G14: Jun
A15: Target (Rs) | B15: 50000 | C15: 55000 | D15: 60000 | E15: 58000 | F15: 62000 | G15: 70000
A17: Sample text (used by TRIM)
A18: Excel is powerful
A20: Loan inputs (used by PMT / FV / PV)
A21: Loan amount (Rs) | B21: 500000
A22: Annual interest rate | B22: 0.09
A23: Tenure (years) | B23: 5
A25: Blue text = sample input values (edit them to see the Functions sheet update).

Sheet Functions
A1: Lab-2 : Excel Functions - Theory + Formula (live examples use the 'Data' sheet)
A3: Sr No | B3: Category | C3: Function | D3: Theory (What it does) | E3: Syntax | F3: Formula Used | G3: Result
A4: 1 | B4: Math & Trig | C4: SUM | D4: Adds all the numbers in a range of cells. | E4: SUM(number1, [number2], ...) | F4: =SUM(Data!E2:E11) | G4: =SUM(Data!E2:E11) -> 490000
A5: 2 | B5: Math & Trig | C5: PRODUCT | D5: Multiplies all the numbers given as arguments. | E5: PRODUCT(number1, [number2], ...) | F5: =PRODUCT(5,4,2) | G5: =PRODUCT(5,4,2) -> 40
A6: 3 | B6: Math & Trig | C6: SUMIF | D6: Adds the cells that meet ONE condition. | E6: SUMIF(range, criteria, [sum_range]) | F6: =SUMIF(Data!C2:C11,"Sales",Data!E2:E11) | G6: =SUMIF(Data!C2:C11,"Sales",Data!E2:E11) -> 168000
A7: 4 | B7: Math & Trig | C7: SUMIFS | D7: Adds the cells that meet MULTIPLE conditions. | E7: SUMIFS(sum_range, criteria_range1, criteria1, ...) | F7: =SUMIFS(Data!E2:E11,Data!C2:C11,"IT",Data!D2:D11,"Pune") | G7: =SUMIFS(Data!E2:E11,Data!C2:C11,"IT",Data!D2:D11,"Pune") -> 58000
A8: 5 | B8: Math & Trig | C8: SUMPRODUCT | D8: Multiplies corresponding values of arrays and returns the sum of those products. | E8: SUMPRODUCT(array1, [array2], ...) | F8: =SUMPRODUCT(Data!E2:E11,Data!H2:H11) | G8: =SUMPRODUCT(Data!E2:E11,Data!H2:H11) -> 1904000
A9: 6 | B9: Math & Trig | C9: ROUND | D9: Rounds a number to a given number of digits. | E9: ROUND(number, num_digits) | F9: =ROUND(3.14159,2) | G9: =ROUND(3.14159,2) -> 3.14
A10: 7 | B10: Math & Trig | C10: ROUNDUP | D10: Always rounds a number UP (away from zero). | E10: ROUNDUP(number, num_digits) | F10: =ROUNDUP(3.141,1) | G10: =ROUNDUP(3.141,1) -> 3.2
A11: 8 | B11: Math & Trig | C11: ROUNDDOWN | D11: Always rounds a number DOWN (towards zero). | E11: ROUNDDOWN(number, num_digits) | F11: =ROUNDDOWN(3.189,1) | G11: =ROUNDDOWN(3.189,1) -> 3.1
A12: 9 | B12: Math & Trig | C12: INT | D12: Rounds a number down to the nearest integer. | E12: INT(number) | F12: =INT(8.9) | G12: =INT(8.9) -> 8
A13: 10 | B13: Math & Trig | C13: ABS | D13: Returns the absolute (positive) value of a number. | E13: ABS(number) | F13: =ABS(-250) | G13: =ABS(-250) -> 250
A14: 11 | B14: Math & Trig | C14: POWER | D14: Returns a number raised to a power. | E14: POWER(number, power) | F14: =POWER(2,5) | G14: =POWER(2,5) -> 32
A15: 12 | B15: Math & Trig | C15: SQRT | D15: Returns the square root of a number. | E15: SQRT(number) | F15: =SQRT(144) | G15: =SQRT(144) -> 12
A16: 13 | B16: Math & Trig | C16: MOD | D16: Returns the remainder after division. | E16: MOD(number, divisor) | F16: =MOD(17,5) | G16: =MOD(17,5) -> 2
A17: 14 | B17: Statistical | C17: AVERAGE | D17: Returns the arithmetic mean of numbers. | E17: AVERAGE(number1, [number2], ...) | F17: =AVERAGE(Data!E2:E11) | G17: =AVERAGE(Data!E2:E11) -> 49000
A18: 15 | B18: Statistical | C18: AVERAGEIF | D18: Average of cells that meet a condition. | E18: AVERAGEIF(range, criteria, [average_range]) | F18: =AVERAGEIF(Data!C2:C11,"IT",Data!E2:E11) | G18: =AVERAGEIF(Data!C2:C11,"IT",Data!E2:E11) -> 61666.667
A19: 16 | B19: Statistical | C19: MIN | D19: Returns the smallest number in a range. | E19: MIN(number1, [number2], ...) | F19: =MIN(Data!E2:E11) | G19: =MIN(Data!E2:E11) -> 38000
A20: 17 | B20: Statistical | C20: MAX | D20: Returns the largest number in a range. | E20: MAX(number1, [number2], ...) | F20: =MAX(Data!E2:E11) | G20: =MAX(Data!E2:E11) -> 65000
A21: 18 | B21: Statistical | C21: COUNT | D21: Counts cells that contain NUMBERS. | E21: COUNT(value1, [value2], ...) | F21: =COUNT(Data!E2:E11) | G21: =COUNT(Data!E2:E11) -> 10
A22: 19 | B22: Statistical | C22: COUNTA | D22: Counts cells that are NOT EMPTY (numbers + text). | E22: COUNTA(value1, [value2], ...) | F22: =COUNTA(Data!B2:B11) | G22: =COUNTA(Data!B2:B11) -> 10
A23: 20 | B23: Statistical | C23: COUNTBLANK | D23: Counts EMPTY cells in a range. | E23: COUNTBLANK(range) | F23: =COUNTBLANK(Data!A2:H12) | G23: =COUNTBLANK(Data!A2:H12) -> 8
A24: 21 | B24: Statistical | C24: COUNTIF | D24: Counts cells that meet ONE condition. | E24: COUNTIF(range, criteria) | F24: =COUNTIF(Data!D2:D11,"Mumbai") | G24: =COUNTIF(Data!D2:D11,"Mumbai") -> 3
A25: 22 | B25: Statistical | C25: COUNTIFS | D25: Counts cells that meet MULTIPLE conditions. | E25: COUNTIFS(range1, criteria1, range2, criteria2, ...) | F25: =COUNTIFS(Data!C2:C11,"Sales",Data!E2:E11,">40000") | G25: =COUNTIFS(Data!C2:C11,"Sales",Data!E2:E11,">40000") -> 3
A26: 23 | B26: Statistical | C26: MEDIAN | D26: Returns the middle value of a set of numbers. | E26: MEDIAN(number1, [number2], ...) | F26: =MEDIAN(Data!E2:E11) | G26: =MEDIAN(Data!E2:E11) -> 46000
A27: 24 | B27: Statistical | C27: MODE | D27: Returns the most frequently occurring value. | E27: MODE(number1, [number2], ...) | F27: =MODE(Data!H2:H11) | G27: =MODE(Data!H2:H11) -> 4
A28: 25 | B28: Statistical | C28: LARGE | D28: Returns the k-th largest value (e.g. 2nd highest). | E28: LARGE(array, k) | F28: =LARGE(Data!E2:E11,2) | G28: =LARGE(Data!E2:E11,2) -> 62000
A29: 26 | B29: Statistical | C29: SMALL | D29: Returns the k-th smallest value. | E29: SMALL(array, k) | F29: =SMALL(Data!E2:E11,2) | G29: =SMALL(Data!E2:E11,2) -> 39000
A30: 27 | B30: Statistical | C30: RANK | D30: Returns the rank of a number within a list. | E30: RANK(number, ref, [order]) | F30: =RANK(Data!E4,Data!E2:E11,0) | G30: =RANK(Data!E4,Data!E2:E11,0) -> 2
A31: 28 | B31: Logical | C31: IF | D31: Checks a condition and returns one value if TRUE and another if FALSE. | E31: IF(logical_test, value_if_true, value_if_false) | F31: =IF(Data!E2>40000,"High Salary","Low Salary") | G31: =IF(Data!E2>40000,"High Salary","Low Salary") -> High Salary
A32: 29 | B32: Logical | C32: Nested IF | D32: An IF inside another IF to test more than two outcomes. | E32: IF(test1, val1, IF(test2, val2, val3)) | F32: =IF(Data!H2>=5,"Excellent",IF(Data!H2>=3,"Good","Poor")) | G32: =IF(Data!H2>=5,"Excellent",IF(Data!H2>=3,"Good","Poor")) -> Good
A33: 30 | B33: Logical | C33: IFS | D33: Tests multiple conditions without nesting (Excel 2019+). | E33: IFS(test1, value1, test2, value2, ...) | F33: =_xlfn.IFS(Data!H3>=5,"Excellent",Data!H3>=3,"Good",TRUE,"Poor") | G33: =_xlfn.IFS(Data!H3>=5,"Excellent",Data!H3>=3,"Good",TRUE(),"Poor") -> Excellent
A34: 31 | B34: Logical | C34: AND | D34: Returns TRUE only if ALL conditions are TRUE. | E34: AND(logical1, [logical2], ...) | F34: =AND(Data!C2="Sales",Data!E2>40000) | G34: =AND(Data!C2="Sales",Data!E2>40000) -> TRUE
A35: 32 | B35: Logical | C35: OR | D35: Returns TRUE if ANY one condition is TRUE. | E35: OR(logical1, [logical2], ...) | F35: =OR(Data!D3="Mumbai",Data!D3="Pune") | G35: =OR(Data!D3="Mumbai",Data!D3="Pune") -> TRUE
A36: 33 | B36: Logical | C36: NOT | D36: Reverses a logical value (TRUE becomes FALSE). | E36: NOT(logical) | F36: =NOT(Data!C2="HR") | G36: =NOT(Data!C2="HR") -> TRUE
A37: 34 | B37: Logical | C37: IFERROR | D37: Returns a custom value if a formula gives an error. | E37: IFERROR(value, value_if_error) | F37: =IFERROR(Data!E2/Data!G3,"Cannot divide by 0") | G37: =IFERROR(Data!E2/Data!G3,"Cannot divide by 0") -> Cannot divide by 0
A38: 35 | B38: Text | C38: CONCATENATE | D38: Joins two or more text strings into one. | E38: CONCATENATE(text1, [text2], ...) | F38: =CONCATENATE(Data!B3," - ",Data!C3) | G38: =CONCATENATE(Data!B3," - ",Data!C3) -> Priya Patil - HR
A39: 36 | B39: Text | C39: CONCAT | D39: Newer version of CONCATENATE; also accepts ranges. | E39: CONCAT(text1, [text2], ...) | F39: =_xlfn.CONCAT(Data!B4," (",Data!D4,")") | G39: =_xlfn.CONCAT(Data!B4," (",Data!D4,")") -> Amit Joshi (Mumbai)
A40: 37 | B40: Text | C40: TEXTJOIN | D40: Joins text with a delimiter and can ignore blanks. | E40: TEXTJOIN(delimiter, ignore_empty, text1, ...) | F40: =_xlfn.TEXTJOIN(", ",TRUE,Data!D2:D5) | G40: =_xlfn.TEXTJOIN(", ",TRUE(),Data!D2:D5) -> Mumbai, Pune, Mumbai, Thane
A41: 38 | B41: Text | C41: & operator | D41: Ampersand joins text just like CONCATENATE. | E41: text1 & text2 | F41: =Data!B5&" works in "&Data!C5 | G41: =Data!B5&" works in "&Data!C5 -> Sneha Kulkarni works in Sales
A42: 39 | B42: Text | C42: LEFT | D42: Extracts characters from the LEFT side of text. | E42: LEFT(text, [num_chars]) | F42: =LEFT(Data!B3,5) | G42: =LEFT(Data!B3,5) -> Priya
A43: 40 | B43: Text | C43: RIGHT | D43: Extracts characters from the RIGHT side of text. | E43: RIGHT(text, [num_chars]) | F43: =RIGHT(Data!B3,5) | G43: =RIGHT(Data!B3,5) -> Patil
A44: 41 | B44: Text | C44: MID | D44: Extracts characters from the MIDDLE of text. | E44: MID(text, start_num, num_chars) | F44: =MID(Data!B4,6,5) | G44: =MID(Data!B4,6,5) -> Joshi
A45: 42 | B45: Text | C45: LEN | D45: Returns the number of characters in text. | E45: LEN(text) | F45: =LEN(Data!B5) | G45: =LEN(Data!B5) -> 14
A46: 43 | B46: Text | C46: UPPER | D46: Converts text to UPPERCASE. | E46: UPPER(text) | F46: =UPPER(Data!B2) | G46: =UPPER(Data!B2) -> RAHUL SHARMA
A47: 44 | B47: Text | C47: LOWER | D47: Converts text to lowercase. | E47: LOWER(text) | F47: =LOWER(Data!B3) | G47: =LOWER(Data!B3) -> priya patil
A48: 45 | B48: Text | C48: PROPER | D48: Capitalises the first letter of each word. | E48: PROPER(text) | F48: =PROPER(Data!B2) | G48: =PROPER(Data!B2) -> Rahul Sharma
A49: 46 | B49: Text | C49: TRIM | D49: Removes extra spaces, leaving single spaces between words. | E49: TRIM(text) | F49: =TRIM(Data!A18) | G49: =TRIM(Data!A18) -> Excel is powerful
A50: 47 | B50: Text | C50: FIND | D50: Returns position of text inside text (case-sensitive). | E50: FIND(find_text, within_text, [start_num]) | F50: =FIND(" ",Data!B3) | G50: =FIND(" ",Data!B3) -> 6
A51: 48 | B51: Text | C51: SEARCH | D51: Returns position of text inside text (NOT case-sensitive). | E51: SEARCH(find_text, within_text, [start_num]) | F51: =SEARCH("PATIL",Data!B3) | G51: =SEARCH("PATIL",Data!B3) -> 7
A52: 49 | B52: Text | C52: SUBSTITUTE | D52: Replaces old text with new text. | E52: SUBSTITUTE(text, old_text, new_text) | F52: =SUBSTITUTE(Data!D2,"Mumbai","Bombay") | G52: =SUBSTITUTE(Data!D2,"Mumbai","Bombay") -> Bombay
A53: 50 | B53: Text | C53: REPLACE | D53: Replaces characters at a given position. | E53: REPLACE(old_text, start_num, num_chars, new_text) | F53: =REPLACE("ABC-2024",5,4,"2026") | G53: =REPLACE("ABC-2024",5,4,"2026") -> ABC-2026
A54: 51 | B54: Text | C54: TEXT | D54: Formats a number/date as text in a given format. | E54: TEXT(value, format_text) | F54: =TEXT(Data!F2,"dd-mmm-yyyy") | G54: =TEXT(Data!F2,"dd-mmm-yyyy") -> 15-Mar-2021
A55: 52 | B55: Text | C55: VALUE | D55: Converts text that looks like a number into a number. | E55: VALUE(text) | F55: =VALUE("1500")+500 | G55: =VALUE("1500")+500 -> 2000
A56: 53 | B56: Text | C56: EXACT | D56: Checks if two texts are exactly the same (case-sensitive). | E56: EXACT(text1, text2) | F56: =EXACT("Excel","excel") | G56: =EXACT("Excel","excel") -> FALSE
A57: 54 | B57: Text | C57: REPT | D57: Repeats text a given number of times. | E57: REPT(text, number_times) | F57: =REPT("*",Data!H2) | G57: =REPT("*",Data!H2) -> ****
A58: 55 | B58: Lookup & Reference | C58: VLOOKUP | D58: Searches a value in the FIRST column of a table and returns a value from the same row (vertical lookup). | E58: VLOOKUP(lookup_value, table_array, col_index_num, [range_lookup]) | F58: =VLOOKUP(105,Data!A2:H11,2,FALSE) | G58: =VLOOKUP(105,Data!A2:H11,2,FALSE()) -> Rohan Mehta
A59: 56 | B59: Lookup & Reference | C59: HLOOKUP | D59: Searches a value in the FIRST row of a table and returns a value from the same column (horizontal lookup). | E59: HLOOKUP(lookup_value, table_array, row_index_num, [range_lookup]) | F59: =HLOOKUP("Mar",Data!B14:G15,2,FALSE) | G59: =HLOOKUP("Mar",Data!B14:G15,2,FALSE()) -> 60000
A60: 57 | B60: Lookup & Reference | C60: INDEX | D60: Returns the value at a given row and column of a range. | E60: INDEX(array, row_num, [column_num]) | F60: =INDEX(Data!B2:B11,4) | G60: =INDEX(Data!B2:B11,4) -> Sneha Kulkarni
A61: 58 | B61: Lookup & Reference | C61: MATCH | D61: Returns the POSITION of a value in a range. | E61: MATCH(lookup_value, lookup_array, [match_type]) | F61: =MATCH("Neha Desai",Data!B2:B11,0) | G61: =MATCH("Neha Desai",Data!B2:B11,0) -> 6
A62: 59 | B62: Lookup & Reference | C62: INDEX + MATCH | D62: Two-way lookup; can look left, more flexible than VLOOKUP. | E62: INDEX(return_range, MATCH(value, lookup_range, 0)) | F62: =INDEX(Data!A2:A11,MATCH("Karan Shah",Data!B2:B11,0)) | G62: =INDEX(Data!A2:A11,MATCH("Karan Shah",Data!B2:B11,0)) -> 107
A63: 60 | B63: Lookup & Reference | C63: XLOOKUP | D63: Modern lookup (Excel 2021/365) that searches any direction and returns a default if not found. | E63: XLOOKUP(lookup_value, lookup_array, return_array, [if_not_found]) | F63: =XLOOKUP("Amit Joshi",Data!B2:B11,Data!E2:E11,"Not found") | G63: 62,000 (in Excel 2021/365; returns Amit Joshi's salary)
A64: 61 | B64: Lookup & Reference | C64: CHOOSE | D64: Returns a value from a list based on an index number. | E64: CHOOSE(index_num, value1, value2, ...) | F64: =CHOOSE(2,"Mon","Tue","Wed") | G64: =CHOOSE(2,"Mon","Tue","Wed") -> Tue
A65: 62 | B65: Lookup & Reference | C65: ROWS / COLUMNS | D65: Returns the number of rows (or columns) in a range. | E65: ROWS(array) / COLUMNS(array) | F65: =ROWS(Data!A2:A11) | G65: =ROWS(Data!A2:A11) -> 10
A66: 63 | B66: Date & Time | C66: TODAY | D66: Returns today's date (updates automatically). | E66: TODAY() | F66: =TODAY() | G66: =TODAY() -> 46323
A67: 64 | B67: Date & Time | C67: NOW | D67: Returns the current date AND time. | E67: NOW() | F67: =NOW() | G67: =NOW() -> 46323.356
A68: 65 | B68: Date & Time | C68: DATE | D68: Creates a date from year, month and day. | E68: DATE(year, month, day) | F68: =DATE(2026,8,15) | G68: =DATE(2026,8,15) -> 46249
A69: 66 | B69: Date & Time | C69: YEAR | D69: Returns the year of a date. | E69: YEAR(serial_number) | F69: =YEAR(Data!F2) | G69: =YEAR(Data!F2) -> 2021
A70: 67 | B70: Date & Time | C70: MONTH | D70: Returns the month (1-12) of a date. | E70: MONTH(serial_number) | F70: =MONTH(Data!F2) | G70: =MONTH(Data!F2) -> 3
A71: 68 | B71: Date & Time | C71: DAY | D71: Returns the day (1-31) of a date. | E71: DAY(serial_number) | F71: =DAY(Data!F2) | G71: =DAY(Data!F2) -> 15
A72: 69 | B72: Date & Time | C72: WEEKDAY | D72: Returns the day of the week as a number (1=Sunday). | E72: WEEKDAY(serial_number, [return_type]) | F72: =WEEKDAY(Data!F2) | G72: =WEEKDAY(Data!F2) -> 2
A73: 70 | B73: Date & Time | C73: DATEDIF | D73: Calculates the difference between two dates in years ("Y"), months ("M") or days ("D"). | E73: DATEDIF(start_date, end_date, unit) | F73: =DATEDIF(Data!F2,DATE(2026,10,28),"Y") | G73: =DATEDIF(Data!F2,DATE(2026,10,28),"Y") -> 5
A74: 71 | B74: Date & Time | C74: NETWORKDAYS | D74: Counts working days (Mon-Fri) between two dates. | E74: NETWORKDAYS(start_date, end_date, [holidays]) | F74: =NETWORKDAYS(DATE(2026,10,1),DATE(2026,10,31)) | G74: =NETWORKDAYS(DATE(2026,10,1),DATE(2026,10,31)) -> 22
A75: 72 | B75: Date & Time | C75: EDATE | D75: Returns the date a given number of months before/after a date. | E75: EDATE(start_date, months) | F75: =EDATE(Data!F2,6) | G75: =EDATE(Data!F2,6) -> 44454
A76: 73 | B76: Date & Time | C76: EOMONTH | D76: Returns the last day of the month, n months away. | E76: EOMONTH(start_date, months) | F76: =EOMONTH(Data!F2,0) | G76: =EOMONTH(Data!F2,0) -> 44286
A77: 74 | B77: Financial | C77: PMT | D77: Calculates the periodic (EMI) payment for a loan. | E77: PMT(rate, nper, pv, [fv], [type]) | F77: =PMT(Data!B22/12,Data!B23*12,-Data!B21) | G77: =PMT(Data!B22/12,Data!B23*12,-Data!B21) -> 10379.178
A78: 75 | B78: Financial | C78: FV | D78: Future value of an investment with regular payments. | E78: FV(rate, nper, pmt, [pv], [type]) | F78: =FV(8%/12,12*10,-5000) | G78: =FV(8%/12,12*10,-5000) -> 914730.18
A79: 76 | B79: Financial | C79: PV | D79: Present value of a series of future payments. | E79: PV(rate, nper, pmt, [fv], [type]) | F79: =PV(9%/12,60,-10000) | G79: =PV(9%/12,60,-10000) -> 481733.74
A80: 77 | B80: Information | C80: ISBLANK | D80: Returns TRUE if a cell is empty. | E80: ISBLANK(value) | F80: =ISBLANK(Data!A12) | G80: =ISBLANK(Data!A12) -> TRUE
A81: 78 | B81: Information | C81: ISNUMBER | D81: Returns TRUE if the value is a number. | E81: ISNUMBER(value) | F81: =ISNUMBER(Data!E2) | G81: =ISNUMBER(Data!E2) -> TRUE
A82: 79 | B82: Information | C82: ISTEXT | D82: Returns TRUE if the value is text. | E82: ISTEXT(value) | F82: =ISTEXT(Data!B2) | G82: =ISTEXT(Data!B2) -> TRUE
